Metadata-Version: 2.1
Name: fookebox
Version: 1.0.1
Summary: A jukebox-style web-frontend to mpd
Home-page: https://code.ott.net/fookebox/
Author: Stefan Ott
Author-email: stefan@ott.net
Project-URL: Source, https://git.ott.net/fookebox/
Classifier: Development Status :: 5 - Production/Stable
Classifier: Environment :: Web Environment
Classifier: Intended Audience :: End Users/Desktop
Classifier: License :: DFSG approved
Classifier: License :: OSI Approved :: GNU Affero General Public License v3
Classifier: Natural Language :: English
Classifier: Natural Language :: German
Classifier: Operating System :: OS Independent
Classifier: Programming Language :: Python
Classifier: Topic :: Multimedia
Classifier: Topic :: Multimedia :: Sound/Audio
Requires-Python: >=3.9
Provides-Extra: dev
Provides-Extra: test
License-File: COPYING
